yolozone/__init__.py
yolozone/objects.py
yolozone/pose.py
yolozone/tracker.py
yolozone-0.0.3.dist-info/METADATA
yolozone-0.0.3.dist-info/WHEEL
yolozone-0.0.3.dist-info/top_level.txt
yolozone-0.0.3.dist-info/RECORD
