Metadata-Version: 2.2
Name: yolozone
Version: 0.0.3
Requires-Dist: numpy>=1.26.4
Requires-Dist: opencv-python>=4.10.0.84
Requires-Dist: ultralytics>=8.3.11
Dynamic: description
Dynamic: description-content-type
Dynamic: requires-dist
